[
  {
    "tags": {},
    "filePath": "../components/src/Menu/Menu.tsx",
    "description": "",
    "displayName": "Menu",
    "methods": [],
    "props": {
      "activator": {
        "defaultValue": null,
        "description": "",
        "name": "activator",
        "parent": {
          "fileName": "packages/components/src/Menu/Menu.types.ts",
          "name": "MenuLegacyProps"
        },
        "required": false,
        "type": {
          "name": "ReactElement<{ [key: string]: unknown; fullWidth?: boolean; onClick?: (event?: MouseEvent<Element, MouseEvent>) => void; }, string | JSXElementConstructor<any>>"
        }
      },
      "items": {
        "defaultValue": null,
        "description": "",
        "name": "items",
        "parent": {
          "fileName": "packages/components/src/Menu/Menu.types.ts",
          "name": "MenuLegacyProps"
        },
        "required": true,
        "type": {
          "name": "SectionProps[]"
        }
      },
      "UNSAFE_className": {
        "defaultValue": null,
        "description": "",
        "name": "UNSAFE_className",
        "parent": {
          "fileName": "packages/components/src/Menu/Menu.types.ts",
          "name": "MenuBaseProps"
        },
        "required": false,
        "type": {
          "name": "{ menu?: string; header?: string; action?: string; }"
        }
      },
      "UNSAFE_style": {
        "defaultValue": null,
        "description": "",
        "name": "UNSAFE_style",
        "parent": {
          "fileName": "packages/components/src/Menu/Menu.types.ts",
          "name": "MenuBaseProps"
        },
        "required": false,
        "type": {
          "name": "{ menu?: CSSProperties; header?: CSSProperties; action?: CSSProperties; }"
        }
      }
    }
  }
]