[
  {
    "tags": {},
    "filePath": "packages/components-native/src/Divider/Divider.tsx",
    "description": "",
    "displayName": "Divider",
    "methods": [],
    "props": {
      "direction": {
        "defaultValue": {
          "value": "horizontal"
        },
        "description": "The direction of the divider",
        "name": "direction",
        "parent": {
          "fileName": "packages/components-native/src/Divider/Divider.tsx",
          "name": "DividerProps"
        },
        "required": false,
        "type": {
          "name": "\"horizontal\" | \"vertical\""
        }
      },
      "size": {
        "defaultValue": {
          "value": "base"
        },
        "description": "The weight of the divider.",
        "name": "size",
        "parent": {
          "fileName": "packages/components-native/src/Divider/Divider.tsx",
          "name": "DividerProps"
        },
        "required": false,
        "type": {
          "name": "\"large\" | \"base\" | \"larger\" | \"largest\""
        }
      },
      "testID": {
        "defaultValue": {
          "value": "Divider"
        },
        "description": "Used to locate this view in end-to-end tests.",
        "name": "testID",
        "parent": {
          "fileName": "packages/components-native/src/Divider/Divider.tsx",
          "name": "DividerProps"
        },
        "required": false,
        "type": {
          "name": "string"
        }
      }
    }
  }
]